marcos_hello_world_package/__init__.py
marcos_hello_world_package-0.1.1.dist-info/WHEEL
marcos_hello_world_package-0.1.1.dist-info/METADATA
marcos_hello_world_package-0.1.1.dist-info/RECORD
